impatial_text_cls/__init__.py
impatial_text_cls/impatial_text_cls.py
impatial_text_cls/utils.py
impartial_text_cls-0.0.2.dist-info/LICENSE
impartial_text_cls-0.0.2.dist-info/METADATA
impartial_text_cls-0.0.2.dist-info/WHEEL
impartial_text_cls-0.0.2.dist-info/top_level.txt
impartial_text_cls-0.0.2.dist-info/RECORD
