Metadata-Version: 2.1
Name: impartial-text-cls
Version: 0.0.2
Summary: Text classifier, based on the BERT and a Bayesian neural network, which can train on small labeled texts and doubt its decision
Home-page: https://github.com/bond005/impartial_text_cls
Author: Ivan Bondarenko
Author-email: bond005@yandex.ru
License: Apache License Version 2.0
Keywords: bert,bayesian,intent,text,nlp,tensorflow,scikit-learn
Platform: UNKNOWN
Classifier: Development Status :: 3 - Alpha
Classifier: Intended Audience :: Science/Research
Classifier: Intended Audience :: Developers
Classifier: Topic :: Software Development
Classifier: Topic :: Scientific/Engineering
Classifier: Topic :: Scientific/Engineering :: Artificial Intelligence
Classifier: Topic :: Text Processing
Classifier: Topic :: Text Processing :: Linguistic
Classifier: License :: OSI Approved :: Apache Software License
Classifier: Programming Language :: Python :: 3.6
Classifier: Programming Language :: Python :: 3.7
Requires-Dist: bert-tensorflow (==1.0.1)
Requires-Dist: nltk (==3.4.4)
Requires-Dist: numpy (==1.16.4)
Requires-Dist: scikit-learn (==0.21.2)
Requires-Dist: scikit-optimize (==0.5.2)
Requires-Dist: tensorflow-gpu (==1.14.0)
Requires-Dist: tensorflow-hub (==0.5.0)
Requires-Dist: tensorflow-probability (==0.7.0)
